sval/__init__.py
sval/hand_representation.py
sval/hand_strengths.py
sval/lookup7card.dat.gz
sval/tests.py
sval-0.1.2.dist-info/LICENSE.txt
sval-0.1.2.dist-info/METADATA
sval-0.1.2.dist-info/WHEEL
sval-0.1.2.dist-info/top_level.txt
sval-0.1.2.dist-info/RECORD
