Metadata-Version: 2.1
Name: sval
Version: 0.1.2
Summary: A fast Hold'em seven card evaluator 
Home-page: https://github.com/cstich/PySval
License: UNKNOWN
Keywords: Texas Hold'em,Hold'em,Poker,7 card,seven card
Platform: UNKNOWN
Classifier: Development Status :: 4 - Beta
Classifier: Intended Audience :: Developers
Classifier: Topic :: Scientific/Engineering :: Artificial Intelligence
Classifier: License :: OSI Approved :: MIT License
Classifier: Programming Language :: Python :: 3
Classifier: Programming Language :: Python :: 3.6
Classifier: Programming Language :: Python :: 3.7
Classifier: Programming Language :: Python :: 3.8
Classifier: Programming Language :: Python :: 3.9
Classifier: Programming Language :: Python :: 3 :: Only
Requires-Python: >=3.6
License-File: LICENSE.txt
Requires-Dist: numba
Requires-Dist: numpy
